{
   "number_epochs": 5,
   "info_used": "partial info",
   "perc_full_data": 0.1,
   "n_epochs_no_selection": 0,
   "Frequency % cutoff": 0.25,
   "hidden_size": 32,
   "random_state": 0,
   "train_errors": [
      0.6691982746124268,
      0.6640130281448364,
      0.6584016680717468,
      0.6515413522720337,
      0.6482183337211609
   ],
   "valid_errors": [
      0.6806222200393677,
      0.6771950721740723
   ],
   "val_epochs": [
      0,
      4
   ],
   "input_data_path": "../data/donated_blood/donated_blood_subsampled_balance.csv",
   "gradwcontext": true,
   "Encompassing Param": 0.1,
   "Normalize Grads & Contx": false,
   "cluster_all_classes": false,
   "imputation method": "",
   "model_dropout": 0.05
}